nonebot_plugin_voicemusic/__init__.py
nonebot_plugin_voicemusic/config.py
nonebot_plugin_voicemusic-0.1.20.dist-info/LICENSE
nonebot_plugin_voicemusic-0.1.20.dist-info/METADATA
nonebot_plugin_voicemusic-0.1.20.dist-info/WHEEL
nonebot_plugin_voicemusic-0.1.20.dist-info/top_level.txt
nonebot_plugin_voicemusic-0.1.20.dist-info/RECORD
