Metadata-Version: 2.1
Name: nonebot-plugin-voicemusic
Version: 0.1.20
Summary: nonebot2语音点歌插件
Author: QiYork
Author-email: 1309946582@qq.com
Project-URL: Homepage, https://github.com/Onimaimai/nonebot-plugin-voicemusic
Classifier: Programming Language :: Python :: 3
Classifier: License :: OSI Approved :: MIT License
Classifier: Operating System :: OS Independent
Requires-Python: >=3.9
License-File: LICENSE
Requires-Dist: nonebot2>=2.2.0
Requires-Dist: nonebot-adapter-onebot>=2.1.5
Requires-Dist: httpx>=0.27.2
